{
    "$schema": "https://schema.management.azure.com/schemas/2019-04-01/deploymentParameters.json#",
    "contentVersion": "1.0.0.0",
    "parameters": {
      "resourceGroupName": {
        "value": "rg-sample-alert"
      },
      "alertRuleName": {
        "value": "ABCRecoveryPointAvailabilityAlert"
      },
      "alertRuleDescription": {
        "value": "Alert rule to be fired if the age of the latest recovery point is more than the time in days provided by the user."
      },
      "alertSeverity": {
        "value": 3
      },
      "alertAggregationGranularity": {
        "value": "P1D"
      },
      "alertEvaluationFrequency": {
        "value": "PT6H"
      },
      "LatestRPAgeThresholdInDays": {
        "value": "2"
      },
      "MSIName": {
        "value": "ABCAlertsMSI"
      },
      "newOrExistingMSI": {
        "value": "new"
      },
      "roleDefinitionId": {
        "value": "acdd72a7-3385-48ef-bd42-f606fba81ae7"
      }
    }
  }