{
  "$schema": "http://schema.management.azure.com/schemas/2015-01-01/deploymentTemplate.json#",
  "contentVersion": "1.0.0.1",
  "parameters": {
    "version":{
      "type":"object"
    },
    "networkSpec": {
      "type": "object"
    }
  },
  "resources": [
    {
      "apiVersion": "[parameters('version').resourceAPIVersion]",
      "type": "Microsoft.Network/virtualNetworks",
      "name": "[parameters('networkSpec').virtualNetworkName]",
      "location": "[resourceGroup().location]",
      "properties": {
        "addressSpace": {
          "addressPrefixes": [
            "[parameters('networkSpec').addressPrefix]"
          ]
        },
        "subnets": [
          {
            "name": "[parameters('networkSpec').virtualNetworkSubnetName]",
            "properties": {
              "addressPrefix": "[parameters('networkSpec').subnetPrefix]"
            }
          }
        ]
      }
    }
  ]
}
