{"id":"https://schema.management.azure.com/schemas/2014-04-01/Microsoft.Sql.json#","$schema":"http://json-schema.org/draft-04/schema#","title":"Microsoft.Sql","description":"Microsoft Sql Resource Types","resourceDefinitions":{"servers":{"type":"object","properties":{"name":{"type":"string","description":"The name of the server."},"type":{"type":"string","enum":["Microsoft.Sql/servers"]},"apiVersion":{"type":"string","enum":["2014-04-01"]},"location":{"type":"string","description":"Resource location."},"tags":{"oneOf":[{"type":"object","additionalProperties":{"type":"string"}},{"$ref":"https://schema.management.azure.com/schemas/2015-01-01/deploymentTemplate.json#/definitions/expression"}],"description":"Resource tags."},"properties":{"oneOf":[{"$ref":"#/definitions/ServerProperties"},{"$ref":"https://schema.management.azure.com/schemas/2015-01-01/deploymentTemplate.json#/definitions/expression"}],"description":"Represents the properties of the resource."},"resources":{"type":"array","items":{"oneOf":[{"$ref":"#/definitions/servers_auditingPolicies_childResource"},{"$ref":"#/definitions/servers_communicationLinks_childResource"},{"$ref":"#/definitions/servers_administrators_childResource"},{"$ref":"#/definitions/servers_firewallRules_childResource"},{"$ref":"#/definitions/servers_elasticPools_childResource"},{"$ref":"#/definitions/servers_disasterRecoveryConfiguration_childResource"},{"$ref":"#/definitions/servers_databases_childResource"},{"$ref":"#/definitions/servers_connectionPolicies_childResource"},{"$ref":"#/definitions/servers_backupLongTermRetentionVaults_childResource"},{"$ref":"#/definitions/servers_advisors_childResource"}]}}},"required":["name","type","apiVersion","location","properties"],"description":"Microsoft.Sql/servers"},"servers_administrators":{"type":"object","properties":{"name":{"oneOf":[{"type":"string"},{"$ref":"https://schema.management.azure.com/schemas/2015-01-01/deploymentTemplate.json#/definitions/expression"}],"description":"Name of the server administrator resource."},"type":{"type":"string","enum":["Microsoft.Sql/servers/administrators"]},"apiVersion":{"type":"string","enum":["2014-04-01"]},"properties":{"oneOf":[{"$ref":"#/definitions/ServerAdministratorProperties"},{"$ref":"https://schema.management.azure.com/schemas/2015-01-01/deploymentTemplate.json#/definitions/expression"}],"description":"The properties of the resource."}},"required":["name","type","apiVersion","properties"],"description":"Microsoft.Sql/servers/administrators"},"servers_advisors":{"type":"object","properties":{"name":{"type":"string"},"type":{"type":"string","enum":["Microsoft.Sql/servers/advisors"]},"apiVersion":{"type":"string","enum":["2014-04-01"]},"properties":{"oneOf":[{"$ref":"#/definitions/AdvisorProperties"},{"$ref":"https://schema.management.azure.com/schemas/2015-01-01/deploymentTemplate.json#/definitions/expression"}],"description":"Resource properties."}},"required":["name","type","apiVersion","properties"],"description":"Microsoft.Sql/servers/advisors"},"servers_auditingPolicies":{"type":"object","properties":{"name":{"oneOf":[{"type":"string"},{"$ref":"https://schema.management.azure.com/schemas/2015-01-01/deploymentTemplate.json#/definitions/expression"}],"description":"The name of the table auditing policy."},"type":{"type":"string","enum":["Microsoft.Sql/servers/auditingPolicies"]},"apiVersion":{"type":"string","enum":["2014-04-01"]},"properties":{"oneOf":[{"$ref":"#/definitions/ServerTableAuditingPolicyProperties"},{"$ref":"https://schema.management.azure.com/schemas/2015-01-01/deploymentTemplate.json#/definitions/expression"}],"description":"Resource properties."}},"required":["name","type","apiVersion","properties"],"description":"Microsoft.Sql/servers/auditingPolicies"},"servers_backupLongTermRetentionVaults":{"type":"object","properties":{"name":{"type":"string"},"type":{"type":"string","enum":["Microsoft.Sql/servers/backupLongTermRetentionVaults"]},"apiVersion":{"type":"string","enum":["2014-04-01"]},"properties":{"oneOf":[{"$ref":"#/definitions/BackupLongTermRetentionVaultProperties"},{"$ref":"https://schema.management.azure.com/schemas/2015-01-01/deploymentTemplate.json#/definitions/expression"}],"description":"The properties of the backup long term retention vault"}},"required":["name","type","apiVersion","properties"],"description":"Microsoft.Sql/servers/backupLongTermRetentionVaults"},"servers_communicationLinks":{"type":"object","properties":{"name":{"type":"string"},"type":{"type":"string","enum":["Microsoft.Sql/servers/communicationLinks"]},"apiVersion":{"type":"string","enum":["2014-04-01"]},"properties":{"oneOf":[{"$ref":"#/definitions/ServerCommunicationLinkProperties"},{"$ref":"https://schema.management.azure.com/schemas/2015-01-01/deploymentTemplate.json#/definitions/expression"}],"description":"The properties of resource."}},"required":["name","type","apiVersion","properties"],"description":"Microsoft.Sql/servers/communicationLinks"},"servers_connectionPolicies":{"type":"object","properties":{"name":{"oneOf":[{"type":"string"},{"$ref":"https://schema.management.azure.com/schemas/2015-01-01/deploymentTemplate.json#/definitions/expression"}],"description":"The name of the connection policy."},"type":{"type":"string","enum":["Microsoft.Sql/servers/connectionPolicies"]},"apiVersion":{"type":"string","enum":["2014-04-01"]},"properties":{"oneOf":[{"$ref":"#/definitions/ServerConnectionPolicyProperties"},{"$ref":"https://schema.management.azure.com/schemas/2015-01-01/deploymentTemplate.json#/definitions/expression"}],"description":"The properties of the server secure connection policy."}},"required":["name","type","apiVersion","properties"],"description":"Microsoft.Sql/servers/connectionPolicies"},"servers_databases":{"type":"object","properties":{"name":{"type":"string"},"type":{"type":"string","enum":["Microsoft.Sql/servers/databases"]},"apiVersion":{"type":"string","enum":["2014-04-01"]},"location":{"type":"string","description":"Resource location."},"tags":{"oneOf":[{"type":"object","additionalProperties":{"type":"string"}},{"$ref":"https://schema.management.azure.com/schemas/2015-01-01/deploymentTemplate.json#/definitions/expression"}],"description":"Resource tags."},"properties":{"oneOf":[{"$ref":"#/definitions/DatabaseProperties"},{"$ref":"https://schema.management.azure.com/schemas/2015-01-01/deploymentTemplate.json#/definitions/expression"}],"description":"The properties representing the resource."},"resources":{"type":"array","items":{"oneOf":[{"$ref":"#/definitions/servers_databases_connectionPolicies_childResource"},{"$ref":"#/definitions/servers_databases_auditingPolicies_childResource"},{"$ref":"#/definitions/servers_databases_transparentDataEncryption_childResource"},{"$ref":"#/definitions/servers_databases_geoBackupPolicies_childResource"},{"$ref":"#/definitions/servers_databases_dataMaskingPolicies_childResource"},{"$ref":"#/definitions/servers_databases_securityAlertPolicies_childResource"},{"$ref":"#/definitions/servers_databases_extensions_childResource"},{"$ref":"#/definitions/servers_databases_backupLongTermRetentionPolicies_childResource"},{"$ref":"#/definitions/servers_databases_advisors_childResource"}]}}},"required":["name","type","apiVersion","location","properties"],"description":"Microsoft.Sql/servers/databases"},"servers_databases_advisors":{"type":"object","properties":{"name":{"type":"string","description":"The name of the Database Advisor."},"type":{"type":"string","enum":["Microsoft.Sql/servers/databases/advisors"]},"apiVersion":{"type":"string","enum":["2014-04-01"]},"properties":{"oneOf":[{"$ref":"#/definitions/AdvisorProperties"},{"$ref":"https://schema.management.azure.com/schemas/2015-01-01/deploymentTemplate.json#/definitions/expression"}],"description":"Resource properties."}},"required":["name","type","apiVersion","properties"],"description":"Microsoft.Sql/servers/databases/advisors"},"servers_databases_auditingPolicies":{"type":"object","properties":{"name":{"oneOf":[{"type":"string"},{"$ref":"https://schema.management.azure.com/schemas/2015-01-01/deploymentTemplate.json#/definitions/expression"}],"description":"The name of the table auditing policy."},"type":{"type":"string","enum":["Microsoft.Sql/servers/databases/auditingPolicies"]},"apiVersion":{"type":"string","enum":["2014-04-01"]},"properties":{"oneOf":[{"$ref":"#/definitions/DatabaseTableAuditingPolicyProperties"},{"$ref":"https://schema.management.azure.com/schemas/2015-01-01/deploymentTemplate.json#/definitions/expression"}],"description":"Resource properties."}},"required":["name","type","apiVersion","properties"],"description":"Microsoft.Sql/servers/databases/auditingPolicies"},"servers_databases_backupLongTermRetentionPolicies":{"type":"object","properties":{"name":{"type":"string"},"type":{"type":"string","enum":["Microsoft.Sql/servers/databases/backupLongTermRetentionPolicies"]},"apiVersion":{"type":"string","enum":["2014-04-01"]},"properties":{"oneOf":[{"$ref":"#/definitions/BackupLongTermRetentionPolicyProperties"},{"$ref":"https://schema.management.azure.com/schemas/2015-01-01/deploymentTemplate.json#/definitions/expression"}],"description":"The properties of the backup long term retention policy"}},"required":["name","type","apiVersion","properties"],"description":"Microsoft.Sql/servers/databases/backupLongTermRetentionPolicies"},"servers_databases_connectionPolicies":{"type":"object","properties":{"name":{"oneOf":[{"type":"string"},{"$ref":"https://schema.management.azure.com/schemas/2015-01-01/deploymentTemplate.json#/definitions/expression"}],"description":"The name of the connection policy."},"type":{"type":"string","enum":["Microsoft.Sql/servers/databases/connectionPolicies"]},"apiVersion":{"type":"string","enum":["2014-04-01"]},"properties":{"oneOf":[{"$ref":"#/definitions/DatabaseConnectionPolicyProperties"},{"$ref":"https://schema.management.azure.com/schemas/2015-01-01/deploymentTemplate.json#/definitions/expression"}],"description":"Resource properties."}},"required":["name","type","apiVersion","properties"],"description":"Microsoft.Sql/servers/databases/connectionPolicies"},"servers_databases_dataMaskingPolicies":{"type":"object","properties":{"name":{"oneOf":[{"type":"string"},{"$ref":"https://schema.management.azure.com/schemas/2015-01-01/deploymentTemplate.json#/definitions/expression"}],"description":"The name of the database for which the data masking rule applies."},"type":{"type":"string","enum":["Microsoft.Sql/servers/databases/dataMaskingPolicies"]},"apiVersion":{"type":"string","enum":["2014-04-01"]},"properties":{"oneOf":[{"$ref":"#/definitions/DataMaskingPolicyProperties"},{"$ref":"https://schema.management.azure.com/schemas/2015-01-01/deploymentTemplate.json#/definitions/expression"}],"description":"The properties of the data masking policy."},"resources":{"type":"array","items":{"oneOf":[{"$ref":"#/definitions/servers_databases_dataMaskingPolicies_rules_childResource"}]}}},"required":["name","type","apiVersion","properties"],"description":"Microsoft.Sql/servers/databases/dataMaskingPolicies"},"servers_databases_dataMaskingPolicies_rules":{"type":"object","properties":{"name":{"type":"string"},"type":{"type":"string","enum":["Microsoft.Sql/servers/databases/dataMaskingPolicies/rules"]},"apiVersion":{"type":"string","enum":["2014-04-01"]},"properties":{"oneOf":[{"$ref":"#/definitions/DataMaskingRuleProperties"},{"$ref":"https://schema.management.azure.com/schemas/2015-01-01/deploymentTemplate.json#/definitions/expression"}],"description":"The properties of the resource."}},"required":["name","type","apiVersion","properties"],"description":"Microsoft.Sql/servers/databases/dataMaskingPolicies/rules"},"servers_databases_extensions":{"type":"object","properties":{"name":{"type":"string"},"type":{"type":"string","enum":["Microsoft.Sql/servers/databases/extensions"]},"apiVersion":{"type":"string","enum":["2014-04-01"]},"properties":{"oneOf":[{"$ref":"#/definitions/ImportExtensionProperties"},{"$ref":"https://schema.management.azure.com/schemas/2015-01-01/deploymentTemplate.json#/definitions/expression"}],"description":"Represents the properties of the resource."}},"required":["name","type","apiVersion","properties"],"description":"Microsoft.Sql/servers/databases/extensions"},"servers_databases_geoBackupPolicies":{"type":"object","properties":{"name":{"oneOf":[{"type":"string"},{"$ref":"https://schema.management.azure.com/schemas/2015-01-01/deploymentTemplate.json#/definitions/expression"}],"description":"The name of the geo backup policy."},"type":{"type":"string","enum":["Microsoft.Sql/servers/databases/geoBackupPolicies"]},"apiVersion":{"type":"string","enum":["2014-04-01"]},"properties":{"oneOf":[{"$ref":"#/definitions/GeoBackupPolicyProperties"},{"$ref":"https://schema.management.azure.com/schemas/2015-01-01/deploymentTemplate.json#/definitions/expression"}],"description":"The properties of the geo backup policy."}},"required":["name","type","apiVersion","properties"],"description":"Microsoft.Sql/servers/databases/geoBackupPolicies"},"servers_databases_securityAlertPolicies":{"type":"object","properties":{"name":{"type":"string"},"type":{"type":"string","enum":["Microsoft.Sql/servers/databases/securityAlertPolicies"]},"apiVersion":{"type":"string","enum":["2014-04-01"]},"location":{"type":"string","description":"The geo-location where the resource lives"},"properties":{"oneOf":[{"$ref":"#/definitions/DatabaseSecurityAlertPolicyProperties"},{"$ref":"https://schema.management.azure.com/schemas/2015-01-01/deploymentTemplate.json#/definitions/expression"}],"description":"Properties of the security alert policy."}},"required":["name","type","apiVersion","properties"],"description":"Microsoft.Sql/servers/databases/securityAlertPolicies"},"servers_databases_transparentDataEncryption":{"type":"object","properties":{"name":{"oneOf":[{"type":"string"},{"$ref":"https://schema.management.azure.com/schemas/2015-01-01/deploymentTemplate.json#/definitions/expression"}],"description":"The name of the transparent data encryption configuration."},"type":{"type":"string","enum":["Microsoft.Sql/servers/databases/transparentDataEncryption"]},"apiVersion":{"type":"string","enum":["2014-04-01"]},"properties":{"oneOf":[{"$ref":"#/definitions/TransparentDataEncryptionProperties"},{"$ref":"https://schema.management.azure.com/schemas/2015-01-01/deploymentTemplate.json#/definitions/expression"}],"description":"Represents the properties of the resource."}},"required":["name","type","apiVersion","properties"],"description":"Microsoft.Sql/servers/databases/transparentDataEncryption"},"servers_disasterRecoveryConfiguration":{"type":"object","properties":{"name":{"type":"string"},"type":{"type":"string","enum":["Microsoft.Sql/servers/disasterRecoveryConfiguration"]},"apiVersion":{"type":"string","enum":["2014-04-01"]}},"required":["name","type","apiVersion"],"description":"Microsoft.Sql/servers/disasterRecoveryConfiguration"},"servers_elasticPools":{"type":"object","properties":{"name":{"type":"string"},"type":{"type":"string","enum":["Microsoft.Sql/servers/elasticPools"]},"apiVersion":{"type":"string","enum":["2014-04-01"]},"location":{"type":"string","description":"Resource location."},"tags":{"oneOf":[{"type":"object","additionalProperties":{"type":"string"}},{"$ref":"https://schema.management.azure.com/schemas/2015-01-01/deploymentTemplate.json#/definitions/expression"}],"description":"Resource tags."},"properties":{"oneOf":[{"$ref":"#/definitions/ElasticPoolProperties"},{"$ref":"https://schema.management.azure.com/schemas/2015-01-01/deploymentTemplate.json#/definitions/expression"}],"description":"The properties representing the resource."}},"required":["name","type","apiVersion","location","properties"],"description":"Microsoft.Sql/servers/elasticPools"},"servers_firewallRules":{"type":"object","properties":{"name":{"type":"string"},"type":{"type":"string","enum":["Microsoft.Sql/servers/firewallRules"]},"apiVersion":{"type":"string","enum":["2014-04-01"]},"properties":{"oneOf":[{"$ref":"#/definitions/FirewallRuleProperties"},{"$ref":"https://schema.management.azure.com/schemas/2015-01-01/deploymentTemplate.json#/definitions/expression"}],"description":"The properties representing the resource."}},"required":["name","type","apiVersion","properties"],"description":"Microsoft.Sql/servers/firewallRules"}},"definitions":{"AdvisorProperties":{"type":"object","properties":{"autoExecuteValue":{"oneOf":[{"type":"string","enum":["Enabled","Disabled","Default"]},{"$ref":"https://schema.management.azure.com/schemas/2015-01-01/deploymentTemplate.json#/definitions/expression"}],"description":"Gets the auto-execute status (whether to let the system execute the recommendations) of this advisor. Possible values are 'Enabled' and 'Disabled'."}},"required":["autoExecuteValue"],"description":"Properties for a Database, Server or Elastic Pool Advisor."},"BackupLongTermRetentionPolicyProperties":{"type":"object","properties":{"state":{"oneOf":[{"type":"string","enum":["Disabled","Enabled"]},{"$ref":"https://schema.management.azure.com/schemas/2015-01-01/deploymentTemplate.json#/definitions/expression"}],"description":"The status of the backup long term retention policy."},"recoveryServicesBackupPolicyResourceId":{"type":"string","description":"The azure recovery services backup protection policy resource id"}},"required":["state","recoveryServicesBackupPolicyResourceId"],"description":"The properties of a backup long term retention policy"},"BackupLongTermRetentionVaultProperties":{"type":"object","properties":{"recoveryServicesVaultResourceId":{"type":"string","description":"The azure recovery services vault resource id"}},"required":["recoveryServicesVaultResourceId"],"description":"The properties of a backup long term retention vault."},"DatabaseConnectionPolicyProperties":{"type":"object","properties":{"securityEnabledAccess":{"type":"string","description":"The state of security access."},"proxyDnsName":{"type":"string","description":"The fully qualified host name of the auditing proxy."},"proxyPort":{"type":"string","description":"The port number of the auditing proxy."},"visibility":{"type":"string","description":"The visibility of the auditing proxy."},"useServerDefault":{"type":"string","description":"Whether server default is enabled or disabled."},"redirectionState":{"type":"string","description":"The state of proxy redirection."},"state":{"type":"string","description":"The connection policy state."}},"description":"Properties of a database connection policy."},"DatabaseProperties":{"type":"object","properties":{"collation":{"type":"string","description":"The collation of the database. If createMode is not Default, this value is ignored."},"createMode":{"oneOf":[{"type":"string","enum":["Copy","Default","NonReadableSecondary","OnlineSecondary","PointInTimeRestore","Recovery","Restore","RestoreLongTermRetentionBackup"]},{"$ref":"https://schema.management.azure.com/schemas/2015-01-01/deploymentTemplate.json#/definitions/expression"}],"description":"Specifies the mode of database creation.\n\nDefault: regular database creation.\n\nCopy: creates a database as a copy of an existing database. sourceDatabaseId must be specified as the resource ID of the source database.\n\nOnlineSecondary/NonReadableSecondary: creates a database as a (readable or nonreadable) secondary replica of an existing database. sourceDatabaseId must be specified as the resource ID of the existing primary database.\n\nPointInTimeRestore: Creates a database by restoring a point in time backup of an existing database. sourceDatabaseId must be specified as the resource ID of the existing database, and restorePointInTime must be specified.\n\nRecovery: Creates a database by restoring a geo-replicated backup. sourceDatabaseId must be specified as the recoverable database resource ID to restore.\n\nRestore: Creates a database by restoring a backup of a deleted database. sourceDatabaseId must be specified. If sourceDatabaseId is the database's original resource ID, then sourceDatabaseDeletionDate must be specified. Otherwise sourceDatabaseId must be the restorable dropped database resource ID and sourceDatabaseDeletionDate is ignored. restorePointInTime may also be specified to restore from an earlier point in time.\n\nRestoreLongTermRetentionBackup: Creates a database by restoring from a long term retention vault. recoveryServicesRecoveryPointResourceId must be specified as the recovery point resource ID.\n\nCopy, NonReadableSecondary, OnlineSecondary and RestoreLongTermRetentionBackup are not supported for DataWarehouse edition."},"sourceDatabaseId":{"type":"string","description":"Conditional. If createMode is Copy, NonReadableSecondary, OnlineSecondary, PointInTimeRestore, Recovery, or Restore, then this value is required. Specifies the resource ID of the source database. If createMode is NonReadableSecondary or OnlineSecondary, the name of the source database must be the same as the new database being created."},"sourceDatabaseDeletionDate":{"type":"string","format":"date-time","description":"Conditional. If createMode is Restore and sourceDatabaseId is the deleted database's original resource id when it existed (as opposed to its current restorable dropped database id), then this value is required. Specifies the time that the database was deleted."},"restorePointInTime":{"type":"string","format":"date-time","description":"Conditional. If createMode is PointInTimeRestore, this value is required. If createMode is Restore, this value is optional. Specifies the point in time (ISO8601 format) of the source database that will be restored to create the new database. Must be greater than or equal to the source database's earliestRestoreDate value."},"recoveryServicesRecoveryPointResourceId":{"type":"string","description":"Conditional. If createMode is RestoreLongTermRetentionBackup, then this value is required. Specifies the resource ID of the recovery point to restore from."},"edition":{"oneOf":[{"type":"string","enum":["Web","Business","Basic","Standard","Premium","PremiumRS","Free","Stretch","DataWarehouse","System","System2"]},{"$ref":"https://schema.management.azure.com/schemas/2015-01-01/deploymentTemplate.json#/definitions/expression"}],"description":"The edition of the database. The DatabaseEditions enumeration contains all the valid editions. If createMode is NonReadableSecondary or OnlineSecondary, this value is ignored. To see possible values, query the capabilities API (/subscriptions/{subscriptionId}/providers/Microsoft.Sql/locations/{locationID}/capabilities) referred to by operationId: \"Capabilities_ListByLocation.\" or use the Azure CLI command `az sql db list-editions -l westus --query [].name`."},"maxSizeBytes":{"type":"string","description":"The max size of the database expressed in bytes. If createMode is not Default, this value is ignored. To see possible values, query the capabilities API (/subscriptions/{subscriptionId}/providers/Microsoft.Sql/locations/{locationID}/capabilities) referred to by operationId: \"Capabilities_ListByLocation.\""},"requestedServiceObjectiveId":{"oneOf":[{"type":"string","pattern":"^[0-9a-fA-F]{8}(-[0-9a-fA-F]{4}){3}-[0-9a-fA-F]{12}$"},{"$ref":"https://schema.management.azure.com/schemas/2015-01-01/deploymentTemplate.json#/definitions/expression"}],"description":"The configured service level objective ID of the database. This is the service level objective that is in the process of being applied to the database. Once successfully updated, it will match the value of currentServiceObjectiveId property. If requestedServiceObjectiveId and requestedServiceObjectiveName are both updated, the value of requestedServiceObjectiveId overrides the value of requestedServiceObjectiveName. To see possible values, query the capabilities API (/subscriptions/{subscriptionId}/providers/Microsoft.Sql/locations/{locationID}/capabilities) referred to by operationId: \"Capabilities_ListByLocation.\" or use the Azure CLI command `az sql db list-editions --location <location> --query [].supportedServiceLevelObjectives[].name` ."},"requestedServiceObjectiveName":{"oneOf":[{"type":"string","enum":["System","System0","System1","System2","System3","System4","System2L","System3L","System4L","Free","Basic","S0","S1","S2","S3","S4","S6","S7","S9","S12","P1","P2","P3","P4","P6","P11","P15","PRS1","PRS2","PRS4","PRS6","DW100","DW200","DW300","DW400","DW500","DW600","DW1000","DW1200","DW1000c","DW1500","DW1500c","DW2000","DW2000c","DW3000","DW2500c","DW3000c","DW6000","DW5000c","DW6000c","DW7500c","DW10000c","DW15000c","DW30000c","DS100","DS200","DS300","DS400","DS500","DS600","DS1000","DS1200","DS1500","DS2000","ElasticPool"]},{"$ref":"https://schema.management.azure.com/schemas/2015-01-01/deploymentTemplate.json#/definitions/expression"}],"description":"The name of the configured service level objective of the database. This is the service level objective that is in the process of being applied to the database. Once successfully updated, it will match the value of serviceLevelObjective property. To see possible values, query the capabilities API (/subscriptions/{subscriptionId}/providers/Microsoft.Sql/locations/{locationID}/capabilities) referred to by operationId: \"Capabilities_ListByLocation.\" or use the Azure CLI command `az sql db list-editions --location <location> --query [].supportedServiceLevelObjectives[].name`."},"elasticPoolName":{"type":"string","description":"The name of the elastic pool the database is in. If elasticPoolName and requestedServiceObjectiveName are both updated, the value of requestedServiceObjectiveName is ignored. Not supported for DataWarehouse edition."},"readScale":{"oneOf":[{"type":"string","enum":["Enabled","Disabled"]},{"$ref":"https://schema.management.azure.com/schemas/2015-01-01/deploymentTemplate.json#/definitions/expression"}],"description":"Conditional. If the database is a geo-secondary, readScale indicates whether read-only connections are allowed to this database or not. Not supported for DataWarehouse edition."},"sampleName":{"oneOf":[{"type":"string","enum":["AdventureWorksLT"]},{"$ref":"https://schema.management.azure.com/schemas/2015-01-01/deploymentTemplate.json#/definitions/expression"}],"description":"Indicates the name of the sample schema to apply when creating this database. If createMode is not Default, this value is ignored. Not supported for DataWarehouse edition."},"zoneRedundant":{"oneOf":[{"type":"boolean"},{"$ref":"https://schema.management.azure.com/schemas/2015-01-01/deploymentTemplate.json#/definitions/expression"}],"description":"Whether or not this database is zone redundant, which means the replicas of this database will be spread across multiple availability zones."}},"description":"Represents the properties of a database."},"DatabaseSecurityAlertPolicyProperties":{"type":"object","properties":{"state":{"oneOf":[{"type":"string","enum":["New","Enabled","Disabled"]},{"$ref":"https://schema.management.azure.com/schemas/2015-01-01/deploymentTemplate.json#/definitions/expression"}],"description":"Specifies the state of the policy. If state is Enabled, storageEndpoint and storageAccountAccessKey are required."},"disabledAlerts":{"type":"string","description":"Specifies the semicolon-separated list of alerts that are disabled, or empty string to disable no alerts. Possible values: Sql_Injection; Sql_Injection_Vulnerability; Access_Anomaly; Usage_Anomaly."},"emailAddresses":{"type":"string","description":"Specifies the semicolon-separated list of e-mail addresses to which the alert is sent."},"emailAccountAdmins":{"oneOf":[{"type":"string","enum":["Enabled","Disabled"]},{"$ref":"https://schema.management.azure.com/schemas/2015-01-01/deploymentTemplate.json#/definitions/expression"}],"description":"Specifies that the alert is sent to the account administrators."},"storageEndpoint":{"type":"string","description":"Specifies the blob storage endpoint (e.g. https://MyAccount.blob.core.windows.net). This blob storage will hold all Threat Detection audit logs. If state is Enabled, storageEndpoint is required."},"storageAccountAccessKey":{"type":"string","description":"Specifies the identifier key of the Threat Detection audit storage account. If state is Enabled, storageAccountAccessKey is required."},"retentionDays":{"oneOf":[{"type":"integer"},{"$ref":"https://schema.management.azure.com/schemas/2015-01-01/deploymentTemplate.json#/definitions/expression"}],"description":"Specifies the number of days to keep in the Threat Detection audit logs."},"useServerDefault":{"oneOf":[{"type":"string","enum":["Enabled","Disabled"]},{"$ref":"https://schema.management.azure.com/schemas/2015-01-01/deploymentTemplate.json#/definitions/expression"}],"description":"Specifies whether to use the default server policy."}},"required":["state"],"description":"Properties for a database Threat Detection policy."},"DatabaseTableAuditingPolicyProperties":{"type":"object","properties":{"auditingState":{"type":"string","description":"The state of the policy."},"auditLogsTableName":{"type":"string","description":"The audit logs table name."},"eventTypesToAudit":{"type":"string","description":"Comma-separated list of event types to audit."},"fullAuditLogsTableName":{"type":"string","description":"The full audit logs table name."},"retentionDays":{"type":"string","description":"The number of days to keep in the audit logs."},"storageAccountKey":{"type":"string","description":"The key of the auditing storage account."},"storageAccountName":{"type":"string","description":"The table storage account name"},"storageAccountResourceGroupName":{"type":"string","description":"The table storage account resource group name"},"storageAccountSecondaryKey":{"type":"string","description":"The secondary key of the auditing storage account."},"storageAccountSubscriptionId":{"oneOf":[{"type":"string","pattern":"^[0-9a-fA-F]{8}(-[0-9a-fA-F]{4}){3}-[0-9a-fA-F]{12}$"},{"$ref":"https://schema.management.azure.com/schemas/2015-01-01/deploymentTemplate.json#/definitions/expression"}],"description":"The table storage subscription Id."},"storageTableEndpoint":{"type":"string","description":"The storage table endpoint."},"useServerDefault":{"type":"string","description":"Whether server default is enabled or disabled."}},"description":"Properties of a database table auditing policy."},"DataMaskingPolicyProperties":{"type":"object","properties":{"dataMaskingState":{"oneOf":[{"type":"string","enum":["Disabled","Enabled"]},{"$ref":"https://schema.management.azure.com/schemas/2015-01-01/deploymentTemplate.json#/definitions/expression"}],"description":"The state of the data masking policy."},"exemptPrincipals":{"type":"string","description":"The list of the exempt principals. Specifies the semicolon-separated list of database users for which the data masking policy does not apply. The specified users receive data results without masking for all of the database queries."}},"required":["dataMaskingState"],"description":"The properties of a database data masking policy."},"DataMaskingRuleProperties":{"type":"object","properties":{"aliasName":{"type":"string","description":"The alias name. This is a legacy parameter and is no longer used."},"ruleState":{"oneOf":[{"type":"string","enum":["Disabled","Enabled"]},{"$ref":"https://schema.management.azure.com/schemas/2015-01-01/deploymentTemplate.json#/definitions/expression"}],"description":"The rule state. Used to delete a rule. To delete an existing rule, specify the schemaName, tableName, columnName, maskingFunction, and specify ruleState as disabled. However, if the rule doesn't already exist, the rule will be created with ruleState set to enabled, regardless of the provided value of ruleState."},"schemaName":{"type":"string","description":"The schema name on which the data masking rule is applied."},"tableName":{"type":"string","description":"The table name on which the data masking rule is applied."},"columnName":{"type":"string","description":"The column name on which the data masking rule is applied."},"maskingFunction":{"oneOf":[{"type":"string","enum":["Default","CCN","Email","Number","SSN","Text"]},{"$ref":"https://schema.management.azure.com/schemas/2015-01-01/deploymentTemplate.json#/definitions/expression"}],"description":"The masking function that is used for the data masking rule."},"numberFrom":{"type":"string","description":"The numberFrom property of the masking rule. Required if maskingFunction is set to Number, otherwise this parameter will be ignored."},"numberTo":{"type":"string","description":"The numberTo property of the data masking rule. Required if maskingFunction is set to Number, otherwise this parameter will be ignored."},"prefixSize":{"type":"string","description":"If maskingFunction is set to Text, the number of characters to show unmasked in the beginning of the string. Otherwise, this parameter will be ignored."},"suffixSize":{"type":"string","description":"If maskingFunction is set to Text, the number of characters to show unmasked at the end of the string. Otherwise, this parameter will be ignored."},"replacementString":{"type":"string","description":"If maskingFunction is set to Text, the character to use for masking the unexposed part of the string. Otherwise, this parameter will be ignored."}},"required":["schemaName","tableName","columnName","maskingFunction"],"description":"The properties of a database data masking rule."},"ElasticPoolProperties":{"type":"object","properties":{"edition":{"oneOf":[{"type":"string","enum":["Basic","Standard","Premium"]},{"$ref":"https://schema.management.azure.com/schemas/2015-01-01/deploymentTemplate.json#/definitions/expression"}],"description":"The edition of the elastic pool."},"dtu":{"oneOf":[{"type":"integer"},{"$ref":"https://schema.management.azure.com/schemas/2015-01-01/deploymentTemplate.json#/definitions/expression"}],"description":"The total shared DTU for the database elastic pool."},"databaseDtuMax":{"oneOf":[{"type":"integer"},{"$ref":"https://schema.management.azure.com/schemas/2015-01-01/deploymentTemplate.json#/definitions/expression"}],"description":"The maximum DTU any one database can consume."},"databaseDtuMin":{"oneOf":[{"type":"integer"},{"$ref":"https://schema.management.azure.com/schemas/2015-01-01/deploymentTemplate.json#/definitions/expression"}],"description":"The minimum DTU all databases are guaranteed."},"storageMB":{"oneOf":[{"type":"integer"},{"$ref":"https://schema.management.azure.com/schemas/2015-01-01/deploymentTemplate.json#/definitions/expression"}],"description":"Gets storage limit for the database elastic pool in MB."},"zoneRedundant":{"oneOf":[{"type":"boolean"},{"$ref":"https://schema.management.azure.com/schemas/2015-01-01/deploymentTemplate.json#/definitions/expression"}],"description":"Whether or not this database elastic pool is zone redundant, which means the replicas of this database will be spread across multiple availability zones."}},"description":"Represents the properties of an elastic pool."},"FirewallRuleProperties":{"type":"object","properties":{"startIpAddress":{"type":"string","description":"The start IP address of the firewall rule. Must be IPv4 format. Use value '0.0.0.0' to represent all Azure-internal IP addresses."},"endIpAddress":{"type":"string","description":"The end IP address of the firewall rule. Must be IPv4 format. Must be greater than or equal to startIpAddress. Use value '0.0.0.0' to represent all Azure-internal IP addresses."}},"required":["startIpAddress","endIpAddress"],"description":"Represents the properties of a server firewall rule."},"GeoBackupPolicyProperties":{"type":"object","properties":{"state":{"oneOf":[{"type":"string","enum":["Disabled","Enabled"]},{"$ref":"https://schema.management.azure.com/schemas/2015-01-01/deploymentTemplate.json#/definitions/expression"}],"description":"The state of the geo backup policy."}},"required":["state"],"description":"The properties of the geo backup policy."},"ImportExtensionProperties":{"type":"object","properties":{"storageKeyType":{"oneOf":[{"type":"string","enum":["StorageAccessKey","SharedAccessKey"]},{"$ref":"https://schema.management.azure.com/schemas/2015-01-01/deploymentTemplate.json#/definitions/expression"}],"description":"The type of the storage key to use."},"storageKey":{"type":"string","description":"The storage key to use.  If storage key type is SharedAccessKey, it must be preceded with a \"?.\""},"storageUri":{"type":"string","description":"The storage uri to use."},"administratorLogin":{"type":"string","description":"The name of the SQL administrator."},"administratorLoginPassword":{"type":"string","description":"The password of the SQL administrator."},"authenticationType":{"oneOf":[{"type":"string","enum":["SQL","ADPassword"]},{"$ref":"https://schema.management.azure.com/schemas/2015-01-01/deploymentTemplate.json#/definitions/expression"}],"description":"The authentication type."},"operationMode":{"oneOf":[{"type":"string","enum":["Import"]},{"$ref":"https://schema.management.azure.com/schemas/2015-01-01/deploymentTemplate.json#/definitions/expression"}],"description":"The type of import operation being performed. This is always Import."}},"required":["storageKeyType","storageKey","storageUri","administratorLogin","administratorLoginPassword","operationMode"],"description":"Represents the properties for an import operation"},"ServerAdministratorProperties":{"type":"object","properties":{"administratorType":{"oneOf":[{"type":"string"},{"$ref":"https://schema.management.azure.com/schemas/2015-01-01/deploymentTemplate.json#/definitions/expression"}],"description":"The type of administrator."},"login":{"type":"string","description":"The server administrator login value."},"sid":{"oneOf":[{"type":"string","pattern":"^[0-9a-fA-F]{8}(-[0-9a-fA-F]{4}){3}-[0-9a-fA-F]{12}$"},{"$ref":"https://schema.management.azure.com/schemas/2015-01-01/deploymentTemplate.json#/definitions/expression"}],"description":"The server administrator Sid (Secure ID)."},"tenantId":{"oneOf":[{"type":"string","pattern":"^[0-9a-fA-F]{8}(-[0-9a-fA-F]{4}){3}-[0-9a-fA-F]{12}$"},{"$ref":"https://schema.management.azure.com/schemas/2015-01-01/deploymentTemplate.json#/definitions/expression"}],"description":"The server Active Directory Administrator tenant id."}},"required":["administratorType","login","sid","tenantId"],"description":"The properties of an server Administrator."},"ServerCommunicationLinkProperties":{"type":"object","properties":{"partnerServer":{"type":"string","description":"The name of the partner server."}},"required":["partnerServer"],"description":"The properties of a server communication link."},"ServerConnectionPolicyProperties":{"type":"object","properties":{"connectionType":{"oneOf":[{"type":"string","enum":["Default","Proxy","Redirect"]},{"$ref":"https://schema.management.azure.com/schemas/2015-01-01/deploymentTemplate.json#/definitions/expression"}],"description":"The server connection type."}},"required":["connectionType"],"description":"The properties of a server secure connection policy."},"ServerProperties":{"type":"object","properties":{"version":{"oneOf":[{"type":"string","enum":["2.0","12.0"]},{"$ref":"https://schema.management.azure.com/schemas/2015-01-01/deploymentTemplate.json#/definitions/expression"}],"description":"The version of the server."},"administratorLogin":{"type":"string","description":"Administrator username for the server. Can only be specified when the server is being created (and is required for creation)."},"administratorLoginPassword":{"type":"string","description":"The administrator login password (required for server creation)."}},"description":"Represents the properties of a server."},"servers_administrators_childResource":{"type":"object","properties":{"name":{"oneOf":[{"type":"string"},{"$ref":"https://schema.management.azure.com/schemas/2015-01-01/deploymentTemplate.json#/definitions/expression"}],"description":"Name of the server administrator resource."},"type":{"type":"string","enum":["administrators"]},"apiVersion":{"type":"string","enum":["2014-04-01"]},"properties":{"oneOf":[{"$ref":"#/definitions/ServerAdministratorProperties"},{"$ref":"https://schema.management.azure.com/schemas/2015-01-01/deploymentTemplate.json#/definitions/expression"}],"description":"The properties of the resource."}},"required":["name","type","apiVersion","properties"],"description":"Microsoft.Sql/servers/administrators"},"servers_advisors_childResource":{"type":"object","properties":{"name":{"type":"string"},"type":{"type":"string","enum":["advisors"]},"apiVersion":{"type":"string","enum":["2014-04-01"]},"properties":{"oneOf":[{"$ref":"#/definitions/AdvisorProperties"},{"$ref":"https://schema.management.azure.com/schemas/2015-01-01/deploymentTemplate.json#/definitions/expression"}],"description":"Resource properties."}},"required":["name","type","apiVersion","properties"],"description":"Microsoft.Sql/servers/advisors"},"servers_auditingPolicies_childResource":{"type":"object","properties":{"name":{"oneOf":[{"type":"string"},{"$ref":"https://schema.management.azure.com/schemas/2015-01-01/deploymentTemplate.json#/definitions/expression"}],"description":"The name of the table auditing policy."},"type":{"type":"string","enum":["auditingPolicies"]},"apiVersion":{"type":"string","enum":["2014-04-01"]},"properties":{"oneOf":[{"$ref":"#/definitions/ServerTableAuditingPolicyProperties"},{"$ref":"https://schema.management.azure.com/schemas/2015-01-01/deploymentTemplate.json#/definitions/expression"}],"description":"Resource properties."}},"required":["name","type","apiVersion","properties"],"description":"Microsoft.Sql/servers/auditingPolicies"},"servers_backupLongTermRetentionVaults_childResource":{"type":"object","properties":{"name":{"type":"string"},"type":{"type":"string","enum":["backupLongTermRetentionVaults"]},"apiVersion":{"type":"string","enum":["2014-04-01"]},"properties":{"oneOf":[{"$ref":"#/definitions/BackupLongTermRetentionVaultProperties"},{"$ref":"https://schema.management.azure.com/schemas/2015-01-01/deploymentTemplate.json#/definitions/expression"}],"description":"The properties of the backup long term retention vault"}},"required":["name","type","apiVersion","properties"],"description":"Microsoft.Sql/servers/backupLongTermRetentionVaults"},"servers_communicationLinks_childResource":{"type":"object","properties":{"name":{"type":"string"},"type":{"type":"string","enum":["communicationLinks"]},"apiVersion":{"type":"string","enum":["2014-04-01"]},"properties":{"oneOf":[{"$ref":"#/definitions/ServerCommunicationLinkProperties"},{"$ref":"https://schema.management.azure.com/schemas/2015-01-01/deploymentTemplate.json#/definitions/expression"}],"description":"The properties of resource."}},"required":["name","type","apiVersion","properties"],"description":"Microsoft.Sql/servers/communicationLinks"},"servers_connectionPolicies_childResource":{"type":"object","properties":{"name":{"oneOf":[{"type":"string"},{"$ref":"https://schema.management.azure.com/schemas/2015-01-01/deploymentTemplate.json#/definitions/expression"}],"description":"The name of the connection policy."},"type":{"type":"string","enum":["connectionPolicies"]},"apiVersion":{"type":"string","enum":["2014-04-01"]},"properties":{"oneOf":[{"$ref":"#/definitions/ServerConnectionPolicyProperties"},{"$ref":"https://schema.management.azure.com/schemas/2015-01-01/deploymentTemplate.json#/definitions/expression"}],"description":"The properties of the server secure connection policy."}},"required":["name","type","apiVersion","properties"],"description":"Microsoft.Sql/servers/connectionPolicies"},"servers_databases_advisors_childResource":{"type":"object","properties":{"name":{"type":"string","description":"The name of the Database Advisor."},"type":{"type":"string","enum":["advisors"]},"apiVersion":{"type":"string","enum":["2014-04-01"]},"properties":{"oneOf":[{"$ref":"#/definitions/AdvisorProperties"},{"$ref":"https://schema.management.azure.com/schemas/2015-01-01/deploymentTemplate.json#/definitions/expression"}],"description":"Resource properties."}},"required":["name","type","apiVersion","properties"],"description":"Microsoft.Sql/servers/databases/advisors"},"servers_databases_auditingPolicies_childResource":{"type":"object","properties":{"name":{"oneOf":[{"type":"string"},{"$ref":"https://schema.management.azure.com/schemas/2015-01-01/deploymentTemplate.json#/definitions/expression"}],"description":"The name of the table auditing policy."},"type":{"type":"string","enum":["auditingPolicies"]},"apiVersion":{"type":"string","enum":["2014-04-01"]},"properties":{"oneOf":[{"$ref":"#/definitions/DatabaseTableAuditingPolicyProperties"},{"$ref":"https://schema.management.azure.com/schemas/2015-01-01/deploymentTemplate.json#/definitions/expression"}],"description":"Resource properties."}},"required":["name","type","apiVersion","properties"],"description":"Microsoft.Sql/servers/databases/auditingPolicies"},"servers_databases_backupLongTermRetentionPolicies_childResource":{"type":"object","properties":{"name":{"type":"string"},"type":{"type":"string","enum":["backupLongTermRetentionPolicies"]},"apiVersion":{"type":"string","enum":["2014-04-01"]},"properties":{"oneOf":[{"$ref":"#/definitions/BackupLongTermRetentionPolicyProperties"},{"$ref":"https://schema.management.azure.com/schemas/2015-01-01/deploymentTemplate.json#/definitions/expression"}],"description":"The properties of the backup long term retention policy"}},"required":["name","type","apiVersion","properties"],"description":"Microsoft.Sql/servers/databases/backupLongTermRetentionPolicies"},"servers_databases_childResource":{"type":"object","properties":{"name":{"type":"string"},"type":{"type":"string","enum":["databases"]},"apiVersion":{"type":"string","enum":["2014-04-01"]},"location":{"type":"string","description":"Resource location."},"tags":{"oneOf":[{"type":"object","additionalProperties":{"type":"string"}},{"$ref":"https://schema.management.azure.com/schemas/2015-01-01/deploymentTemplate.json#/definitions/expression"}],"description":"Resource tags."},"properties":{"oneOf":[{"$ref":"#/definitions/DatabaseProperties"},{"$ref":"https://schema.management.azure.com/schemas/2015-01-01/deploymentTemplate.json#/definitions/expression"}],"description":"The properties representing the resource."},"resources":{"type":"array","items":{"oneOf":[{"$ref":"#/definitions/servers_databases_connectionPolicies_childResource"},{"$ref":"#/definitions/servers_databases_auditingPolicies_childResource"},{"$ref":"#/definitions/servers_databases_transparentDataEncryption_childResource"},{"$ref":"#/definitions/servers_databases_geoBackupPolicies_childResource"},{"$ref":"#/definitions/servers_databases_dataMaskingPolicies_childResource"},{"$ref":"#/definitions/servers_databases_securityAlertPolicies_childResource"},{"$ref":"#/definitions/servers_databases_extensions_childResource"}]}}},"required":["name","type","apiVersion","location","properties"],"description":"Microsoft.Sql/servers/databases"},"servers_databases_connectionPolicies_childResource":{"type":"object","properties":{"name":{"oneOf":[{"type":"string"},{"$ref":"https://schema.management.azure.com/schemas/2015-01-01/deploymentTemplate.json#/definitions/expression"}],"description":"The name of the connection policy."},"type":{"type":"string","enum":["connectionPolicies"]},"apiVersion":{"type":"string","enum":["2014-04-01"]},"properties":{"oneOf":[{"$ref":"#/definitions/DatabaseConnectionPolicyProperties"},{"$ref":"https://schema.management.azure.com/schemas/2015-01-01/deploymentTemplate.json#/definitions/expression"}],"description":"Resource properties."}},"required":["name","type","apiVersion","properties"],"description":"Microsoft.Sql/servers/databases/connectionPolicies"},"servers_databases_dataMaskingPolicies_childResource":{"type":"object","properties":{"name":{"oneOf":[{"type":"string"},{"$ref":"https://schema.management.azure.com/schemas/2015-01-01/deploymentTemplate.json#/definitions/expression"}],"description":"The name of the database for which the data masking rule applies."},"type":{"type":"string","enum":["dataMaskingPolicies"]},"apiVersion":{"type":"string","enum":["2014-04-01"]},"properties":{"oneOf":[{"$ref":"#/definitions/DataMaskingPolicyProperties"},{"$ref":"https://schema.management.azure.com/schemas/2015-01-01/deploymentTemplate.json#/definitions/expression"}],"description":"The properties of the data masking policy."},"resources":{"type":"array","items":{"oneOf":[{"$ref":"#/definitions/servers_databases_dataMaskingPolicies_rules_childResource"}]}}},"required":["name","type","apiVersion","properties"],"description":"Microsoft.Sql/servers/databases/dataMaskingPolicies"},"servers_databases_dataMaskingPolicies_rules_childResource":{"type":"object","properties":{"name":{"type":"string"},"type":{"type":"string","enum":["rules"]},"apiVersion":{"type":"string","enum":["2014-04-01"]},"properties":{"oneOf":[{"$ref":"#/definitions/DataMaskingRuleProperties"},{"$ref":"https://schema.management.azure.com/schemas/2015-01-01/deploymentTemplate.json#/definitions/expression"}],"description":"The properties of the resource."}},"required":["name","type","apiVersion","properties"],"description":"Microsoft.Sql/servers/databases/dataMaskingPolicies/rules"},"servers_databases_extensions_childResource":{"type":"object","properties":{"name":{"type":"string"},"type":{"type":"string","enum":["extensions"]},"apiVersion":{"type":"string","enum":["2014-04-01"]},"properties":{"oneOf":[{"$ref":"#/definitions/ImportExtensionProperties"},{"$ref":"https://schema.management.azure.com/schemas/2015-01-01/deploymentTemplate.json#/definitions/expression"}],"description":"Represents the properties of the resource."}},"required":["name","type","apiVersion","properties"],"description":"Microsoft.Sql/servers/databases/extensions"},"servers_databases_geoBackupPolicies_childResource":{"type":"object","properties":{"name":{"oneOf":[{"type":"string"},{"$ref":"https://schema.management.azure.com/schemas/2015-01-01/deploymentTemplate.json#/definitions/expression"}],"description":"The name of the geo backup policy."},"type":{"type":"string","enum":["geoBackupPolicies"]},"apiVersion":{"type":"string","enum":["2014-04-01"]},"properties":{"oneOf":[{"$ref":"#/definitions/GeoBackupPolicyProperties"},{"$ref":"https://schema.management.azure.com/schemas/2015-01-01/deploymentTemplate.json#/definitions/expression"}],"description":"The properties of the geo backup policy."}},"required":["name","type","apiVersion","properties"],"description":"Microsoft.Sql/servers/databases/geoBackupPolicies"},"servers_databases_securityAlertPolicies_childResource":{"type":"object","properties":{"name":{"type":"string"},"type":{"type":"string","enum":["securityAlertPolicies"]},"apiVersion":{"type":"string","enum":["2014-04-01"]},"location":{"type":"string","description":"The geo-location where the resource lives"},"properties":{"oneOf":[{"$ref":"#/definitions/DatabaseSecurityAlertPolicyProperties"},{"$ref":"https://schema.management.azure.com/schemas/2015-01-01/deploymentTemplate.json#/definitions/expression"}],"description":"Properties of the security alert policy."}},"required":["name","type","apiVersion","properties"],"description":"Microsoft.Sql/servers/databases/securityAlertPolicies"},"servers_databases_transparentDataEncryption_childResource":{"type":"object","properties":{"name":{"oneOf":[{"type":"string"},{"$ref":"https://schema.management.azure.com/schemas/2015-01-01/deploymentTemplate.json#/definitions/expression"}],"description":"The name of the transparent data encryption configuration."},"type":{"type":"string","enum":["transparentDataEncryption"]},"apiVersion":{"type":"string","enum":["2014-04-01"]},"properties":{"oneOf":[{"$ref":"#/definitions/TransparentDataEncryptionProperties"},{"$ref":"https://schema.management.azure.com/schemas/2015-01-01/deploymentTemplate.json#/definitions/expression"}],"description":"Represents the properties of the resource."}},"required":["name","type","apiVersion","properties"],"description":"Microsoft.Sql/servers/databases/transparentDataEncryption"},"servers_disasterRecoveryConfiguration_childResource":{"type":"object","properties":{"name":{"type":"string"},"type":{"type":"string","enum":["disasterRecoveryConfiguration"]},"apiVersion":{"type":"string","enum":["2014-04-01"]}},"required":["name","type","apiVersion"],"description":"Microsoft.Sql/servers/disasterRecoveryConfiguration"},"servers_elasticPools_childResource":{"type":"object","properties":{"name":{"type":"string"},"type":{"type":"string","enum":["elasticPools"]},"apiVersion":{"type":"string","enum":["2014-04-01"]},"location":{"type":"string","description":"Resource location."},"tags":{"oneOf":[{"type":"object","additionalProperties":{"type":"string"}},{"$ref":"https://schema.management.azure.com/schemas/2015-01-01/deploymentTemplate.json#/definitions/expression"}],"description":"Resource tags."},"properties":{"oneOf":[{"$ref":"#/definitions/ElasticPoolProperties"},{"$ref":"https://schema.management.azure.com/schemas/2015-01-01/deploymentTemplate.json#/definitions/expression"}],"description":"The properties representing the resource."}},"required":["name","type","apiVersion","location","properties"],"description":"Microsoft.Sql/servers/elasticPools"},"servers_firewallRules_childResource":{"type":"object","properties":{"name":{"type":"string"},"type":{"type":"string","enum":["firewallRules"]},"apiVersion":{"type":"string","enum":["2014-04-01"]},"properties":{"oneOf":[{"$ref":"#/definitions/FirewallRuleProperties"},{"$ref":"https://schema.management.azure.com/schemas/2015-01-01/deploymentTemplate.json#/definitions/expression"}],"description":"The properties representing the resource."}},"required":["name","type","apiVersion","properties"],"description":"Microsoft.Sql/servers/firewallRules"},"ServerTableAuditingPolicyProperties":{"type":"object","properties":{"auditingState":{"type":"string","description":"The state of the policy."},"auditLogsTableName":{"type":"string","description":"The audit logs table name."},"eventTypesToAudit":{"type":"string","description":"Comma-separated list of event types to audit."},"fullAuditLogsTableName":{"type":"string","description":"The full audit logs table name."},"retentionDays":{"type":"string","description":"The number of days to keep in the audit logs."},"storageAccountKey":{"type":"string","description":"The key of the auditing storage account."},"storageAccountName":{"type":"string","description":"The table storage account name"},"storageAccountResourceGroupName":{"type":"string","description":"The table storage account resource group name"},"storageAccountSecondaryKey":{"type":"string","description":"The secondary key of the auditing storage account."},"storageAccountSubscriptionId":{"oneOf":[{"type":"string","pattern":"^[0-9a-fA-F]{8}(-[0-9a-fA-F]{4}){3}-[0-9a-fA-F]{12}$"},{"$ref":"https://schema.management.azure.com/schemas/2015-01-01/deploymentTemplate.json#/definitions/expression"}],"description":"The table storage subscription Id."},"storageTableEndpoint":{"type":"string","description":"The storage table endpoint."}},"description":"Properties of a server table auditing policy."},"TransparentDataEncryptionProperties":{"type":"object","properties":{"status":{"oneOf":[{"type":"string","enum":["Enabled","Disabled"]},{"$ref":"https://schema.management.azure.com/schemas/2015-01-01/deploymentTemplate.json#/definitions/expression"}],"description":"The status of the database transparent data encryption."}},"description":"Represents the properties of a database transparent data encryption."}}}