{
    "$schema": "https://schema.management.azure.com/schemas/2019-04-01/deploymentParameters.json#",
    "contentVersion": "1.0.0.0",
    "parameters": {
        "dnsZone": {
            "value": "GET-PREREQ-dnsZone"
        },
        "dnsZoneRG": {
            "value": "GET-PREREQ-dnsZoneRG"
        },
        "singleZoneOrMultiZone": {
            "value": "noha"
        },
        "adminUsername": {
            "value": "GEN-UNIQUE"
        },
        "openshiftUsername": {
            "value": "GEN-UNIQUE"
        },
        "openshiftPassword": {
            "value": "GEN-PASSWORD"
        },
        "apiKey": {
            "reference": "GEN-KEYVAULT-CLOUDPAK-APIKEY-REFERENCE"
        },
        "sshPublicKey": {
            "value": "GEN-SSH-PUB-KEY"
        },
        "pullSecret": {
          "reference": "GEN-KEYVAULT-OPENSHIFT-PULLSECRET-REFERENCE"
        },
        "aadClientId": {
            "value": "see readme.md for details on how to create the SP"
        },
        "aadClientSecret": {
            "value": "see readme.md for details on how to create the SP"
        },
        "clusterResourceGroupName":{
            "value": "GEN-UNIQUE"
        }
    }
}
