{
  "$schema": "http://schema.management.azure.com/schemas/2015-01-01/deploymentParameters.json#",
  "contentVersion": "1.0.0.0",
  "parameters": {
    "namePrefix": {
      "value": "hpc"
    },
    "location": {
      "value": "West US"
    },
    "headNodeVMSize": {
      "value": "Standard_A4"
    },
    "computeNodeNumber": {
      "value": 2
    },
    "computeNodeVMSize": {
      "value": "Standard_A3"
    },
    "computeNamePrefix": {
      "value": "AzureCN-"
    },
    "storageAccountType": {
      "value": "Standard_LRS"
    },
    "computeNodeSourceImageName": {
      "value": " "
    },
    "computeNodeSourceImageContainer": {
      "value": " "
    },
    "adminUsername": {
      "value": "azureuser"
    },
    "adminPassword": {
      "value": "!!123abc"
    }
  }
}
